graphgenerator/__init__.py
graphgenerator/cli.py
graphgenerator/version.py
graphgenerator/config/__init__.py
graphgenerator/config/column_names.py
graphgenerator/config/config_export.py
graphgenerator/custom_classes/GraphBuilder.py
graphgenerator/custom_classes/__init__.py
graphgenerator/data_cleaning/__init__.py
graphgenerator/data_cleaning/edges.py
graphgenerator/data_cleaning/export.py
graphgenerator/data_cleaning/nodes.py
graphgenerator/utils/__init__.py
graphgenerator/utils/toolbox.py
graphgenerator/utils/tweet_extraction.py
social_networks_graph_generator-1.2.0.dist-info/METADATA
social_networks_graph_generator-1.2.0.dist-info/WHEEL
social_networks_graph_generator-1.2.0.dist-info/dependency_links.txt
social_networks_graph_generator-1.2.0.dist-info/entry_points.txt
social_networks_graph_generator-1.2.0.dist-info/top_level.txt
social_networks_graph_generator-1.2.0.dist-info/RECORD
